doxyqml/__init__.py
doxyqml/lexer.py
doxyqml/main.py
doxyqml/qmlclass.py
doxyqml/qmlparser.py
doxyqml-0.5.1.dist-info/LICENSE
doxyqml-0.5.1.dist-info/METADATA
doxyqml-0.5.1.dist-info/WHEEL
doxyqml-0.5.1.dist-info/entry_points.txt
doxyqml-0.5.1.dist-info/top_level.txt
doxyqml-0.5.1.dist-info/RECORD
