Metadata-Version: 2.1
Name: doxyqml
Version: 0.5.1
Summary: Doxygen input filter for QML files
Home-page: http://agateau.com/projects/doxyqml
Author: Aurélien Gâteau
Author-email: mail@agateau.com
License: BSD
Platform: any
Classifier: Development Status :: 5 - Production/Stable
Classifier: Environment :: Plugins
Classifier: Intended Audience :: Developers
Classifier: License :: OSI Approved :: BSD License
Classifier: Operating System :: OS Independent
Classifier: Programming Language :: Python :: 3
Classifier: Topic :: Documentation
